CODSEQCP/__init__.py
CODSEQCP/codseqcp.py
CODSEQCP/run_augustus.py
CODSEQCP/run_spades.py
codseqcp-0.0.1.dist-info/METADATA
codseqcp-0.0.1.dist-info/WHEEL
codseqcp-0.0.1.dist-info/top_level.txt
codseqcp-0.0.1.dist-info/RECORD
